{
    "HISTORICAL_TOTAL": {
        "FR": "passages depuis la mise en service",
        "EN": "cyclists since beginning"
    },
    "YEAR_TOTAL": {
        "FR": "passages cette année",
        "EN": "cyclists this year"
    },
    "MONTH_TOTAL": {
        "FR": "passages ce mois",
        "EN": "cyclists this month"
    },
    "FIRST": {
        "FR": "premier",
        "EN": "first"
    },
    "SECOND": {
        "FR": "deuxième",
        "EN": "second"
    },
    "THIRD": {
        "FR": "troisième",
        "EN": "third"
    },
    "ITH": {
        "FR": "ème",
        "EN": "th"
    },
    "FEMALE_BEST": {
        "FR": "meilleure",
        "EN": "best"
    },
    "MALE_BEST": {
        "FR": "meilleur",
        "EN": "best"
    },
    "MONDAY": {
        "FR": "lundi",
        "EN": "monday"
    },
    "TUESDAY": {
        "FR": "mardi",
        "EN": "tuesday"
    },
    "WEDNESDAY": {
        "FR": "mercredi",
        "EN": "wednesday"
    },
    "THURSDAY": {
        "FR": "jeudi",
        "EN": "thursday"
    },
    "FRIDAY": {
        "FR": "vendredi",
        "EN": "friday"
    },
    "SATURDAY": {
        "FR": "samedi",
        "EN": "saturday"
    },
    "SUNDAY": {
        "FR": "dimanche",
        "EN": "sunday"
    },
    "SINCE_BEGINING": {
        "FR": "de l'histoire",
        "EN": "in history"
    },
    "SINCE_BEGINING_OF_YEAR": {
        "FR": "de l'année",
        "EN": "of the year"
    },
    "SINCE_BEGINING_OF_MONTH": {
        "FR": "du mois",
        "EN": "of the month"
    },
    "DAY_OF_MONTH": {
        "FR": "jour du mois",
        "EN": "day of the month"
    },
    "DAY_OF_YEAR": {
        "FR": "jour de l'année",
        "EN": "day of the year"
    },
    "DAY_OF_HISTORY": {
        "FR": "jour de l'histoire",
        "EN": "day in history"
    },
    "MONTH_OF_YEAR": {
        "FR": "mois de l'année",
        "EN": "month of the year"
    },
    "MONTH_OF_HISTORY": {
        "FR": "mois de l'histoire",
        "EN": "month of history"
    },
    "YEAR_OF_HISTORY": {
        "FR": "année de l'histoire",
        "EN": "year in history"
    },
    "YESTERDAY": {
        "FR": "hier",
        "EN": "yesterday"
    },
    "TODAY": {
        "FR": "aujourd'hui",
        "EN": "today"
    },
    "ON_DAY": {
        "FR": "le",
        "EN": "on"
    }
}